wink_sdk_inventory/__init__.py
wink_sdk_inventory/api_client.py
wink_sdk_inventory/api_response.py
wink_sdk_inventory/configuration.py
wink_sdk_inventory/exceptions.py
wink_sdk_inventory/py.typed
wink_sdk_inventory/rest.py
wink_sdk_inventory/api/__init__.py
wink_sdk_inventory/api/inventory_api.py
wink_sdk_inventory/api/shareable_link_api.py
wink_sdk_inventory/models/__init__.py
wink_sdk_inventory/models/abstract_open_graph_redirect_url_non_authenticated_entity.py
wink_sdk_inventory/models/activity_lightweight_non_authenticated_entity.py
wink_sdk_inventory/models/activity_localized_inventory_non_authenticated_entity.py
wink_sdk_inventory/models/activity_localized_inventory_with_hotel_best_price_non_authenticated_entity.py
wink_sdk_inventory/models/add_on_lightweight_non_authenticated_entity.py
wink_sdk_inventory/models/add_on_localized_inventory_non_authenticated_entity.py
wink_sdk_inventory/models/add_on_localized_inventory_with_hotel_best_price_non_authenticated_entity.py
wink_sdk_inventory/models/add_on_non_authenticated_entity.py
wink_sdk_inventory/models/address_non_authenticated_entity.py
wink_sdk_inventory/models/advanced_map_configuration_non_authenticated_entity.py
wink_sdk_inventory/models/aggregate_activity_request_non_authenticated_entity.py
wink_sdk_inventory/models/aggregate_add_on_request_non_authenticated_entity.py
wink_sdk_inventory/models/aggregate_attraction_request_non_authenticated_entity.py
wink_sdk_inventory/models/aggregate_greendex_answers_non_authenticated_entity.py
wink_sdk_inventory/models/aggregate_greendex_score_by_category_non_authenticated_entity.py
wink_sdk_inventory/models/aggregate_guest_room_request_non_authenticated_entity.py
wink_sdk_inventory/models/aggregate_hotel_request_non_authenticated_entity.py
wink_sdk_inventory/models/aggregate_inventory_grid_item_request_non_authenticated_entity.py
wink_sdk_inventory/models/aggregate_meeting_room_request_non_authenticated_entity.py
wink_sdk_inventory-0.0.57.dist-info/licenses/LICENSE
wink_sdk_inventory-0.0.57.dist-info/METADATA
wink_sdk_inventory-0.0.57.dist-info/WHEEL
wink_sdk_inventory-0.0.57.dist-info/top_level.txt
wink_sdk_inventory-0.0.57.dist-info/RECORD
